MANIFEST.in
README.rst
setup.py
django_cache_management/VERSION
django_cache_management/__init__.py
django_cache_management/models.py
django_cache_management.egg-info/PKG-INFO
django_cache_management.egg-info/SOURCES.txt
django_cache_management.egg-info/dependency_links.txt
django_cache_management.egg-info/requires.txt
django_cache_management.egg-info/top_level.txt
django_cache_management/management/__init__.py
django_cache_management/management/commands/__init__.py
django_cache_management/management/commands/clearcache.py
django_cache_management/management/commands/listcaches.py
django_cache_management/management/commands/pingcache.py