Metadata-Version: 1.1
Name: django-cache-management
Version: 5.0.0
Summary: Cache management for Django.
Home-page: https://github.com/lddubeau/django-cache-management
Author: Louis-Dominique Dubeau
Author-email: ldd@lddubeau.com
License: MPL 2.0
Keywords: Django,caching
Platform: UNKNOWN
Classifier: Programming Language :: Python
Classifier: Programming Language :: Python :: 3
Classifier: Programming Language :: Python :: 3 :: Only
Classifier: Programming Language :: Python :: 3.6
Classifier: Programming Language :: Python :: 3.7
Classifier: Programming Language :: Python :: 3.8
Classifier: Development Status :: 5 - Production/Stable
Classifier: Intended Audience :: Developers
Classifier: License :: OSI Approved :: Mozilla Public License 2.0 (MPL 2.0)
Classifier: Operating System :: POSIX
Classifier: Framework :: Django
Classifier: Framework :: Django :: 2.2
Classifier: Framework :: Django :: 3.0
Classifier: Framework :: Django :: 3.1
Classifier: Topic :: Software Development :: Libraries
Classifier: Topic :: Utilities
